schemadict/__init__.py
schemadict/__version__.py
schemadict/schemadict.py
schemadict-0.0.12.dist-info/LICENSE.txt
schemadict-0.0.12.dist-info/METADATA
schemadict-0.0.12.dist-info/WHEEL
schemadict-0.0.12.dist-info/top_level.txt
schemadict-0.0.12.dist-info/RECORD
