Metadata-Version: 2.1
Name: schemadict
Version: 0.0.12
Summary: Validate Python dictionaries like JSON schema
Home-page: https://github.com/airinnova/schemadict/
Author: Aaron Dettmann
Author-email: dettmann@kth.se
License: Apache License 2.0
Platform: UNKNOWN
Classifier: Programming Language :: Python :: 3
Classifier: Programming Language :: Python :: 3.6
Classifier: License :: OSI Approved :: Apache Software License
Classifier: Operating System :: OS Independent
Classifier: Environment :: Console
Classifier: Intended Audience :: Developers
Classifier: Topic :: Scientific/Engineering
Requires-Python: >=3.6.0
